json_api_doc/__init__.py
json_api_doc/__main__.py
json_api_doc/deserialization.py
json_api_doc/serialization.py
json_api_doc-0.15.0.dist-info/LICENSE
json_api_doc-0.15.0.dist-info/METADATA
json_api_doc-0.15.0.dist-info/WHEEL
json_api_doc-0.15.0.dist-info/entry_points.txt
json_api_doc-0.15.0.dist-info/top_level.txt
json_api_doc-0.15.0.dist-info/RECORD
