Metadata-Version: 2.1
Name: json-api-doc
Version: 0.15.0
Summary: JSON API to document parser
Home-page: https://github.com/noplay/json-api-doc
Author: Julien Duponchelle
Author-email: julien@duponchelle.info
License: Apache Software License 2.0
Keywords: json api
Platform: UNKNOWN
Classifier: Development Status :: 2 - Pre-Alpha
Classifier: Intended Audience :: Developers
Classifier: License :: OSI Approved :: Apache Software License
Classifier: Natural Language :: English
Classifier: Programming Language :: Python :: 3
Classifier: Programming Language :: Python :: 3.5
Classifier: Programming Language :: Python :: 3.6
